FuelSDKWrapper.py
FuelSDKWrapper-1.3.4.dist-info/LICENSE
FuelSDKWrapper-1.3.4.dist-info/METADATA
FuelSDKWrapper-1.3.4.dist-info/WHEEL
FuelSDKWrapper-1.3.4.dist-info/top_level.txt
FuelSDKWrapper-1.3.4.dist-info/RECORD
