Metadata-Version: 2.1
Name: FuelSDKWrapper
Version: 1.3.4
Summary: Simplify and enhance the FuelSDK for Salesforce Marketing Cloud (ExactTarget)
Home-page: https://github.com/seb-angel/FuelSDK-Python-Wrapper
Author: Seb Angel
Author-email: seb.angel.force@gmail.com
License: MIT
Platform: UNKNOWN
Classifier: Development Status :: 5 - Production/Stable
Classifier: Intended Audience :: Developers
Classifier: License :: OSI Approved :: MIT License
Classifier: Operating System :: OS Independent
Classifier: Topic :: Software Development :: Libraries
Classifier: Programming Language :: Python :: 2.7
Classifier: Programming Language :: Python :: 3
Requires-Dist: Salesforce-FuelSDK (>=1.3.0)
Requires-Dist: PyJWT (>=0.1.9)
Requires-Dist: requests (>=2.18.4)
Requires-Dist: suds-jurko (>=0.6)
